{
  "id": "maggic_cohort",
  "resourceType": "Population",
  "url": "https://ai4hf.eu/cohorts/maggic",
  "name": "maggic_cohort",
  "title": "Patients with Diagnosis of Heart Failure",
  "description": "This cohort includes patients with a diagnosis of heart failure.",
  "version": "1.1",
  "date": "2025-07-21",
  "status": "active",
  "publisher": "AI4HF Team (SRDC Corp.)",
  "entity": [
    {
      "name": "pid",
      "description": "A unique identifier assigned to each patient in the cohort."
    }
  ],
  "entry": [
    {
      "name": "withHeartFailure",
      "description": "Selects the patients diagnosed with heart failure",
      "definesPeriod": true
    }
  ],
  "exit": [
    {
      "name": "deceased",
      "description": "When a patient dies, they are removed from the population/cohort."
    }
  ],
  "period": {
    "description": "Includes all patients for the defined cohort population.",
    "events": "all"
  }
}
